LICENSE
README.md
bin/README.md
bin/__init__.py
bin/main.py
config/README.md
config/__init__.py
config/cli.py
config/config.py
config/constants.py
config/helpers/README.md
config/helpers/__init__.py
config/logconf.py
kinopt/README.md
kinopt/__init__.py
kinopt/evol/README.md
kinopt/evol/__init__.py
kinopt/evol/__main__.py
kinopt/evol/config/__init__.py
kinopt/evol/config/constants.py
kinopt/evol/config/helpers/__init__.py
kinopt/evol/config/logconf.py
kinopt/evol/exporter/__init__.py
kinopt/evol/exporter/helpers/__init__.py
kinopt/evol/exporter/plotout.py
kinopt/evol/exporter/sheetutils.py
kinopt/evol/objfn/__init__.py
kinopt/evol/objfn/minfndiffevo.py
kinopt/evol/objfn/minfnnsgaii.py
kinopt/evol/opt/__init__.py
kinopt/evol/opt/optrun.py
kinopt/evol/optcon/__init__.py
kinopt/evol/optcon/construct.py
kinopt/evol/utils/__init__.py
kinopt/evol/utils/iodata.py
kinopt/evol/utils/params.py
kinopt/fitanalysis/__init__.py
kinopt/fitanalysis/__main__.py
kinopt/fitanalysis/helpers/__init__.py
kinopt/fitanalysis/helpers/postfit.py
kinopt/local/README.md
kinopt/local/__init__.py
kinopt/local/__main__.py
kinopt/local/config/__init__.py
kinopt/local/config/constants.py
kinopt/local/config/helpers/__init__.py
kinopt/local/config/logconf.py
kinopt/local/exporter/__init__.py
kinopt/local/exporter/helpers/__init__.py
kinopt/local/exporter/plotout.py
kinopt/local/exporter/sheetutils.py
kinopt/local/objfn/__init__.py
kinopt/local/objfn/minfn.py
kinopt/local/opt/__init__.py
kinopt/local/opt/optrun.py
kinopt/local/optcon/__init__.py
kinopt/local/optcon/construct.py
kinopt/local/utils/__init__.py
kinopt/local/utils/iodata.py
kinopt/local/utils/params.py
kinopt/optimality/KKT.py
kinopt/optimality/README.md
kinopt/optimality/__init__.py
models/README.md
models/__init__.py
models/diagram/__init__.py
models/diagram/helpers.py
models/distmod.py
models/randmod.py
models/succmod.py
models/testmod.py
models/weights.py
paramest/README.md
paramest/__init__.py
paramest/adapest.py
paramest/core.py
phoskintime-0.3.0.dist-info/LICENSE
phoskintime-0.3.0.dist-info/METADATA
phoskintime-0.3.0.dist-info/WHEEL
phoskintime-0.3.0.dist-info/entry_points.txt
phoskintime-0.3.0.dist-info/RECORD
