Metadata-Version: 2.1
Name: phoskintime
Version: 0.3.0
Summary: PhosKinTime is a Python toolkit for ODE‑based modeling of phosphorylation kinetics and transcriptional time‑series, featuring parameter estimation, sensitivity analysis, steady‑state computation, and interactive visualization.
Home-page: https://bibymaths.github.io/phoskintime/
License: BSD-3-Clause
Keywords: phosphorylation,ODE,time-series,kinetics,parameter-estimation,sensitivity-analysis,systems-biology,LC-MS,modeling,python
Author: Abhinav Mishra
Author-email: mishraabhinav36@gmail.com
Requires-Python: >=3.10,<3.14
Classifier: Development Status :: 4 - Beta
Classifier: Intended Audience :: Science/Research
Classifier: License :: OSI Approved :: BSD License
Classifier: Operating System :: OS Independent
Classifier: Programming Language :: Python :: 3
Classifier: Programming Language :: Python :: 3.10
Classifier: Programming Language :: Python :: 3.11
Classifier: Programming Language :: Python :: 3.12
Classifier: Programming Language :: Python :: 3.13
Classifier: Topic :: Scientific/Engineering :: Bio-Informatics
Classifier: Topic :: Scientific/Engineering :: Mathematics
Requires-Dist: XlsxWriter
Requires-Dist: adjusttext
Requires-Dist: cobyqa
Requires-Dist: graphviz
Requires-Dist: matplotlib
Requires-Dist: mygene
Requires-Dist: numba
Requires-Dist: numpy
Requires-Dist: openpyxl
Requires-Dist: pandas
Requires-Dist: plotly
Requires-Dist: py2cytoscape
Requires-Dist: pymoo
Requires-Dist: python-dotenv
Requires-Dist: salib
Requires-Dist: scikit-learn
Requires-Dist: scipy
Requires-Dist: seaborn
Requires-Dist: statsmodels
Requires-Dist: tqdm
Requires-Dist: typer
Project-URL: Documentation, https://bibymaths.github.io/phoskintime/
Project-URL: Repository, https://github.com/bibymaths/phoskintime
